reproducibility/__init__.py
reproducibility/git.py
reproducibility/py.typed
reproducibility/seed.py
reproducibility/system.py
reproducibility/types.py
reproducibility/version.py
reproducibility-9.0.0.dist-info/METADATA
reproducibility-9.0.0.dist-info/WHEEL
reproducibility-9.0.0.dist-info/RECORD
