Metadata-Version: 2.4
Name: reproducibility
Version: 9.0.0
Summary: A collection of code for reproducibility.
Project-URL: Homepage, https://github.com/gao-hongnan/reproducibility
Project-URL: Issues, https://github.com/gao-hongnan/reproducibility/issues
Author-email: GAO Hongnan <hongnangao@gmail.com>
Classifier: License :: OSI Approved :: Apache Software License
Classifier: Operating System :: OS Independent
Classifier: Programming Language :: Python :: 3
Classifier: Programming Language :: Python :: 3.12
Classifier: Programming Language :: Python :: 3.13
Requires-Python: >=3.12
Requires-Dist: psutil>=6.0.0
Requires-Dist: pydantic>=2.11.9
Provides-Extra: with-numpy-and-torch
Requires-Dist: numpy>=2.3.3; extra == 'with-numpy-and-torch'
Requires-Dist: torch>=2.8.0; extra == 'with-numpy-and-torch'
